odoo/addons/web_widget_x2many_2d_matrix/README.rst
odoo/addons/web_widget_x2many_2d_matrix/__init__.py
odoo/addons/web_widget_x2many_2d_matrix/__manifest__.py
odoo/addons/web_widget_x2many_2d_matrix/i18n/ar.po
odoo/addons/web_widget_x2many_2d_matrix/i18n/de.po
odoo/addons/web_widget_x2many_2d_matrix/i18n/es.po
odoo/addons/web_widget_x2many_2d_matrix/i18n/fi.po
odoo/addons/web_widget_x2many_2d_matrix/i18n/fr.po
odoo/addons/web_widget_x2many_2d_matrix/i18n/hr.po
odoo/addons/web_widget_x2many_2d_matrix/i18n/it.po
odoo/addons/web_widget_x2many_2d_matrix/i18n/lt.po
odoo/addons/web_widget_x2many_2d_matrix/i18n/nl_NL.po
odoo/addons/web_widget_x2many_2d_matrix/i18n/pt_BR.po
odoo/addons/web_widget_x2many_2d_matrix/i18n/sl.po
odoo/addons/web_widget_x2many_2d_matrix/i18n/tr.po
odoo/addons/web_widget_x2many_2d_matrix/i18n/web_widget_x2many_2d_matrix.pot
odoo/addons/web_widget_x2many_2d_matrix/i18n/zh_CN.po
odoo/addons/web_widget_x2many_2d_matrix/readme/CONTRIBUTORS.rst
odoo/addons/web_widget_x2many_2d_matrix/readme/DESCRIPTION.rst
odoo/addons/web_widget_x2many_2d_matrix/readme/HISTORY.rst
odoo/addons/web_widget_x2many_2d_matrix/readme/ROADMAP.rst
odoo/addons/web_widget_x2many_2d_matrix/readme/USAGE.rst
odoo/addons/web_widget_x2many_2d_matrix/static/description/icon.png
odoo/addons/web_widget_x2many_2d_matrix/static/description/index.html
odoo/addons/web_widget_x2many_2d_matrix/static/description/screenshot.png
odoo/addons/web_widget_x2many_2d_matrix/static/src/js/2d_matrix_renderer.js
odoo/addons/web_widget_x2many_2d_matrix/static/src/js/2d_matrix_view.js
odoo/addons/web_widget_x2many_2d_matrix/static/src/js/abstract_view_matrix_limit_extend.js
odoo/addons/web_widget_x2many_2d_matrix/static/src/js/widget_x2many_2d_matrix.js
odoo/addons/web_widget_x2many_2d_matrix/static/src/scss/web_widget_x2many_2d_matrix.scss
odoo/addons/web_widget_x2many_2d_matrix/views/assets.xml
odoo13_addon_web_widget_x2many_2d_matrix-13.0.1.1.1.dist-info/METADATA
odoo13_addon_web_widget_x2many_2d_matrix-13.0.1.1.1.dist-info/WHEEL
odoo13_addon_web_widget_x2many_2d_matrix-13.0.1.1.1.dist-info/top_level.txt
odoo13_addon_web_widget_x2many_2d_matrix-13.0.1.1.1.dist-info/RECORD
