Metadata-Version: 2.1
Name: odoo13-addon-web-widget-x2many-2d-matrix
Version: 13.0.1.1.1
Summary: Show list fields as a matrix
Home-page: https://github.com/OCA/web
Author: Therp BV, Tecnativa, Camptocamp, Brainbean Apps, Odoo Community Association (OCA)
Author-email: support@odoo-community.org
License: AGPL-3
Platform: UNKNOWN
Classifier: Programming Language :: Python
Classifier: Framework :: Odoo
Classifier: License :: OSI Approved :: GNU Affero General Public License v3
Requires-Python: >=3.5
Requires-Dist: odoo (<13.1dev,>=13.0a)
